besked_central/__init__.py
besked_central/sql/initialize.sql
besked_central/sql/schema.sql
besked_central/static/style.css
besked_central/static/images/CP-KB-logo.png
besked_central/static/js/tab-navigation.js
besked_central/templates/apidocs/dashboard.html.jinja
besked_central/templates/auth/login.html.jinja
besked_central/templates/base/base.html.jinja
besked_central/templates/base/dashboard-page.html.jinja
besked_central/templates/base/single-page.html.jinja
besked_central/templates/events/dashboard.html.jinja
besked_central/templates/tracks/dashboard.html.jinja
besked_central/templates/tracks/register.html.jinja
besked_central/templates/tracks/update.html.jinja
besked_central/templates/users/dashboard.html.jinja
besked_central/templates/users/register.html.jinja
besked_central/templates/users/update.html.jinja
cpv_besked_central-1.0.3.dist-info/METADATA
cpv_besked_central-1.0.3.dist-info/WHEEL
cpv_besked_central-1.0.3.dist-info/top_level.txt
cpv_besked_central-1.0.3.dist-info/RECORD
