Metadata-Version: 2.1
Name: cpv-besked-central
Version: 1.0.3
Requires-Dist: flask
Requires-Dist: flask-jwt-extended
Requires-Dist: flask-cors
